{
  "data": [
    {
      "latest_tracked": false,
      "last_lap": {
        "lap_time": 10166,
        "lap_num": 122
      },
      "fastest_lap": {
        "lap_time": 10091,
        "lap_num": 77
      },
      "avg_lap_time": 35160,
      "lap_count": 122,
      "pilot": {
        "team": "",
        "quad": "ZMR",
        "deleted_at": null,
        "transponder_token": "11",
        "image": {
          "url": null
        },
        "name": "Test pilot 11",
        "id": 11
      },
      "position": 1
    },
    {
      "latest_tracked": false,
      "last_lap": {
        "lap_time": 10949,
        "lap_num": 140
      },
      "fastest_lap": {
        "lap_time": 10769,
        "lap_num": 137
      },
      "avg_lap_time": 34554,
      "lap_count": 140,
      "pilot": {
        "team": "",
        "quad": "ZMR",
        "deleted_at": null,
        "transponder_token": "3",
        "image": {
          "url": null
        },
        "name": "Test pilot 03",
        "id": 3
      },
      "position": 2
    },
    {
      "latest_tracked": false,
      "last_lap": {
        "lap_time": 19521,
        "lap_num": 139
      },
      "fastest_lap": {
        "lap_time": 10012,
        "lap_num": 50
      },
      "avg_lap_time": 36864,
      "lap_count": 139,
      "pilot": {
        "team": "",
        "quad": "ZMR",
        "deleted_at": null,
        "transponder_token": "8",
        "image": {
          "url": null
        },
        "name": "Test pilot 08",
        "id": 8
      },
      "position": 3
    },
    {
      "latest_tracked": false,
      "last_lap": {
        "lap_time": 26789,
        "lap_num": 122
      },
      "fastest_lap": {
        "lap_time": 10721,
        "lap_num": 68
      },
      "avg_lap_time": 34817,
      "lap_count": 122,
      "pilot": {
        "team": "",
        "quad": "ZMR",
        "deleted_at": null,
        "transponder_token": "12",
        "image": {
          "url": null
        },
        "name": "Test pilot 12",
        "id": 12
      },
      "position": 4
    },
    {
      "latest_tracked": false,
      "last_lap": {
        "lap_time": 26810,
        "lap_num": 140
      },
      "fastest_lap": {
        "lap_time": 10386,
        "lap_num": 112
      },
      "avg_lap_time": 35312,
      "lap_count": 140,
      "pilot": {
        "team": "",
        "quad": "ZMR",
        "deleted_at": null,
        "transponder_token": "5",
        "image": {
          "url": null
        },
        "name": "Test pilot 05",
        "id": 5
      },
      "position": 5
    },
    {
      "latest_tracked": false,
      "last_lap": {
        "lap_time": 30000,
        "lap_num": 1
      },
      "fastest_lap": {
        "lap_time": 30000,
        "lap_num": 1
      },
      "avg_lap_time": 30000,
      "lap_count": 1,
      "pilot": {
        "team": "",
        "quad": "Foxy",
        "deleted_at": null,
        "transponder_token": "63",
        "image": {
          "url": null
        },
        "name": "fape",
        "id": 13
      },
      "position": 6
    },
    {
      "latest_tracked": true,
      "last_lap": {
        "lap_time": 30442,
        "lap_num": 139
      },
      "fastest_lap": {
        "lap_time": 10006,
        "lap_num": 101
      },
      "avg_lap_time": 34811,
      "lap_count": 139,
      "pilot": {
        "team": "",
        "quad": "ZMR",
        "deleted_at": null,
        "transponder_token": "9",
        "image": {
          "url": null
        },
        "name": "Test pilot 09",
        "id": 9
      },
      "position": 7
    },
    {
      "latest_tracked": false,
      "last_lap": {
        "lap_time": 37012,
        "lap_num": 143
      },
      "fastest_lap": {
        "lap_time": 10017,
        "lap_num": 69
      },
      "avg_lap_time": 34764,
      "lap_count": 143,
      "pilot": {
        "team": "",
        "quad": "ZMR",
        "deleted_at": null,
        "transponder_token": "2",
        "image": {
          "url": null
        },
        "name": "Test pilot 02",
        "id": 2
      },
      "position": 8
    },
    {
      "latest_tracked": false,
      "last_lap": {
        "lap_time": 40077,
        "lap_num": 140
      },
      "fastest_lap": {
        "lap_time": 10796,
        "lap_num": 15
      },
      "avg_lap_time": 35913,
      "lap_count": 140,
      "pilot": {
        "team": "",
        "quad": "ZMR",
        "deleted_at": null,
        "transponder_token": "6",
        "image": {
          "url": null
        },
        "name": "Test pilot 06",
        "id": 6
      },
      "position": 9
    },
    {
      "latest_tracked": false,
      "last_lap": {
        "lap_time": 43939,
        "lap_num": 122
      },
      "fastest_lap": {
        "lap_time": 10407,
        "lap_num": 71
      },
      "avg_lap_time": 35220,
      "lap_count": 122,
      "pilot": {
        "team": "",
        "quad": "ZMR",
        "deleted_at": null,
        "transponder_token": "10",
        "image": {
          "url": null
        },
        "name": "Test pilot 10",
        "id": 10
      },
      "position": 10
    },
    {
      "latest_tracked": false,
      "last_lap": {
        "lap_time": 48055,
        "lap_num": 139
      },
      "fastest_lap": {
        "lap_time": 10001,
        "lap_num": 112
      },
      "avg_lap_time": 34213,
      "lap_count": 139,
      "pilot": {
        "team": "",
        "quad": "ZMR",
        "deleted_at": null,
        "transponder_token": "7",
        "image": {
          "url": null
        },
        "name": "Test pilot 07",
        "id": 7
      },
      "position": 11
    },
    {
      "latest_tracked": false,
      "last_lap": {
        "lap_time": 52942,
        "lap_num": 141
      },
      "fastest_lap": {
        "lap_time": 10260,
        "lap_num": 47
      },
      "avg_lap_time": 33143,
      "lap_count": 141,
      "pilot": {
        "team": "",
        "quad": "ZMR",
        "deleted_at": null,
        "transponder_token": "4",
        "image": {
          "url": null
        },
        "name": "Test pilot 04",
        "id": 4
      },
      "position": 12
    },
    {
      "latest_tracked": false,
      "last_lap": {
        "lap_time": 57137,
        "lap_num": 144
      },
      "fastest_lap": {
        "lap_time": 10840,
        "lap_num": 34
      },
      "avg_lap_time": 34061,
      "lap_count": 144,
      "pilot": {
        "team": "",
        "quad": "ZMR",
        "deleted_at": null,
        "transponder_token": "1",
        "image": {
          "url": null
        },
        "name": "Test pilot 01",
        "id": 1
      },
      "position": 13
    }
  ],
  "session": {
    "current_lap_count": 144,
    "maps_laps": 0,
    "title": "Test Standard Race"
  }
}
